api/__init__.py
api/rate_limiter.py
api/routes.py
api/websocket.py
chain_analysis/__init__.py
chain_analysis/blockchain_listener.py
chain_analysis/liquidity_tracker.py
chain_analysis/memecoin_detector.py
chain_analysis/transaction_analyzer.py
chain_analysis/wallet_profiler.py
score_aggregator/__init__.py
score_aggregator/index_generator.py
score_aggregator/metric_calculator.py
score_aggregator/risk_scorer.py
sentiment_analysis/__init__.py
sentiment_analysis/embedding_models.py
sentiment_analysis/nlp_processor.py
sentiment_analysis/sentiment_scorer.py
sentiment_analysis/social_momentum_analyzer.py
sentiment_analysis/social_scraper.py
temporal_analysis/__init__.py
temporal_analysis/flash_crash_detector.py
temporal_analysis/lstm_predictor.py
temporal_analysis/momentum_tracker.py
temporal_analysis/volatility_calculator.py
whale_detection/__init__.py
whale_detection/accumulation_analyzer.py
whale_detection/market_acceleration_analyzer.py
whale_detection/whale_tracker.py
cades-1.0.0.dist-info/LICENSE
cades-1.0.0.dist-info/METADATA
cades-1.0.0.dist-info/WHEEL
cades-1.0.0.dist-info/top_level.txt
cades-1.0.0.dist-info/RECORD
