Metadata-Version: 2.2
Name: cades
Version: 1.0.0
Summary: Advanced AI system for detecting anomalous patterns in cryptocurrency markets
Home-page: https://github.com/joengo72/crypto-anomaly-detection-engine-system
Author: CADES Team
Author-email: CADE Team <contact@cades.io>
License: MIT License
Project-URL: Homepage, https://cades.io
Project-URL: Repository, https://github.com/joengo72/crypto-anomaly-detection-engine-system
Project-URL: Issues, https://github.com/joengo72/crypto-anomaly-detection-engine-system/issues
Platform: Linux
Platform: MacOS X
Classifier: Development Status :: 5 - Production/Stable
Classifier: Intended Audience :: Financial and Insurance Industry
Classifier: Topic :: Scientific/Engineering :: Artificial Intelligence
Classifier: Topic :: Office/Business :: Financial :: Investment
Classifier: Programming Language :: Python :: 3.9
Classifier: Programming Language :: Python :: 3.10
Classifier: Programming Language :: Python :: 3.11
Classifier: Operating System :: POSIX :: Linux
Classifier: Operating System :: MacOS :: MacOS X
Classifier: Environment :: GPU :: NVIDIA CUDA :: 11.8
Classifier: Framework :: AsyncIO
Classifier: Framework :: FastAPI
Classifier: Natural Language :: English
Requires-Python: >=3.9
License-File: LICENSE
Dynamic: author
Dynamic: home-page
Dynamic: platform
Dynamic: requires-python
